Workbook

Sheet Portada
A1: Seguros Barú, S.A. — Cierres IFRS 17 de 2023, 2024 y 2025
A2: Aseguradora ficticia; datos sintéticos generados con semilla fija. Cifras en USD.
A4: Leyenda
A5: Azul | B5: valor calculado por el motor en Python (src/ifrs17)
A6: Negro | B6: fórmula de Excel
A7: Verde | B7: vínculo a otra hoja
A8: Fondo verde claro | B8: celda de control: debe ser cero
A10: Hoja | B10: Contenido
A11: EEFF | B11: Estado de situación financiera (par. 78-79) y de resultados y ORI (par. 80-92)
A12: Conc_100 | B12: Conciliación LRC sin componente de pérdida, componente de pérdida y LIC (par. 100, 103)
A13: Conc_101 | B13: Conciliación de valor presente, ajuste por riesgo y CSM, contratos GMM y reaseguro (par. 101, 104)
A14: Ingresos_106 | B14: Análisis de los ingresos por seguros de los grupos GMM (par. 106)
A15: NegocioNuevo_107 | B15: Efecto de los contratos reconocidos en el periodo (par. 107)
A16: CSM_109 | B16: Reconocimiento esperado del CSM por bandas de años (par. 109)
A17: Supuestos | B17: Supuestos, curvas de descuento y nivel de confianza (par. 117, 119, 120)
... A21: Controles | B21: Resumen de todas las celdas de control

Sheet EEFF
A1: Estados financieros
A2: Sin impuesto sobre la renta (fuera de alcance). Presentación con NIC 1; ver el anexo IFRS 18 al final.
A4: Estado de situación financiera | B4: 31-dic-2023 | C4: 31-dic-2024 | D4: 31-dic-2025
A5: Inversiones a valor razonable con cambios en resultados | B5: 14299160 | C5: 27410252 | D5: 41779310
A6: Inversiones a valor razonable con cambios en ORI | B6: 20000000 | C6: 20017693 | D6: 20000000
A7: Activos por contratos de seguro | B7: 0 | C7: 0 | D7: 38473.159
A8: Activos por contratos de reaseguro cedido | B8: 844071.92 | C8: 2083847.4 | D8: 3035118.4
A9: Total activos | B9: =SUM(B5:B8) -> 35143232 | C9: =SUM(C5:C8) -> 49511792 | D9: =SUM(D5:D8) -> 64852902
A11: Pasivos por contratos de seguro | B11: 14550189 | C11: 28066153 | D11: 39272810
A13: Capital social | B13: 20000000 | C13: 20000000 | D13: 20000000
A14: Resultados acumulados | B14: =B35 -> 593622.93 | C14: =B14+C35 -> 2608745.1 | D14: =C14+D35 -> 5857942.6
A15: Reserva de finanzas de seguros (ORI) | B15: =B38+B39 -> -579.97655 | C15: =B15+C38+C39 -> 45520.959 | D15: =C15+D38+D39 -> 129270.19
A16: Reserva de inversiones a valor razonable con cambios en ORI | B16: =B40 -> 0 | C16: =B16+C40 -> -1208627.2 | D16: =C16+D40 -> -407121.57
A17: Total patrimonio | B17: =SUM(B13:B16) -> 20593043 | C17: =SUM(C13:C16) -> 21445639 | D17: =SUM(D13:D16) -> 25580091
A18: Control: activos - pasivos - patrimonio | B18: =B9-B11-B17 -> 0 | C18: =C9-C11-C17 -> 0 | D18: =D9-D11-D17 -> 0
A22: Estado de resultados y otro resultado integral | B22: 2023 | C22: 2024 | D22: 2025
A23: Ingresos por seguros | B23: 9780724.3 | C23: 21995636 | D23: 26742566
A24: Gastos del servicio de seguros | B24: -9402411.9 | C24: -19796288 | D24: -23580953
A25: Resultado neto de los contratos de reaseguro cedido | B25: 72221.7 | C25: -311236.34 | D25: -610562.75
A26: Resultado del servicio de seguros | B26: =SUM(B23:B25) -> 450534.08 | C26: =SUM(C23:C25) -> 1888112.6 | D26: =SUM(D23:D25) -> 2551051.2
A28: Ingresos de inversiones | B28: 1279596 | C28: 1761017.4 | D28: 2232567.1
A29: Gastos financieros de seguros emitidos | B29: 69650.905 | C29: -428758.71 | D29: -326366.44
A30: Ingresos financieros del reaseguro cedido | B30: 13219.207 | C30: 40519.167 | D30: 87039.887
A31: Resultado financiero neto | B31: =SUM(B28:B30) -> 1362466.1 | C31: =SUM(C28:C30) -> 1372777.9 | D31: =SUM(D28:D30) -> 1993240.6
A33: Otros gastos de operación (no atribuibles, B66(d)) | B33: -1219377.2 | C33: -1245768.4 | D33: -1295094.2
A35: Resultado del año antes de impuestos | B35: =B26+B31+B33 -> 593622.93 | C35: =C26+C31+C33 -> 2015122.1 | D35: =D26+D31+D33 -> 3249197.6
A37: Otro resultado integral (partidas que se reclasificarán)
A38: Finanzas de seguros emitidos | B38: -25501.892 | C38: 108963.98 | D38: 58759.951
A39: Finanzas del reaseguro cedido | B39: 24921.916 | C39: -62863.047 | D39: 24989.276
A40: Inversiones a valor razonable con cambios en ORI | B40: 0 | C40: -1208627.2 | D40: 801505.63
A42: Resultado integral total | B42: =B35+SUM(B38:B40) -> 593042.96 | C42: =C35+SUM(C38:C40) -> 852595.86 | D42: =D35+SUM(D38:D40) -> 4134452.4
A43: Control: resultado de la fórmula - resultado del motor | B43: =B35-593622.933065355 -> 0 | C43: =C35-2015122.1254712 -> 0 | D43: =D35-3249197.58347216 -> 0

Sheet Conc_100
A1: Conciliación del pasivo por cobertura restante y por siniestros incurridos (par. 100, 103)
A2: Contratos emitidos por portafolio. Los saldos iniciales de 2024 y 2025 son el saldo final del año anterior (fórmula).
A4: Vida temporal
A5: Vida temporal — 2023 | B5: LRC sin componente de pérdida | C5: Componente de pérdida | D5: LIC | E5: Total
A6: Saldo inicial | B6: 0 | C6: 0 | D6: 0 | E6: =SUM(B6:D6) -> 0
A7: Ingresos por seguros | B7: -1189126.7 | C7: 0 | D7: 0 | E7: =SUM(B7:D7) -> -1189126.7
A8: Siniestros y otros gastos incurridos | B8: 0 | C8: 0 | D8: 1026865.5 | E8: =SUM(B8:D8) -> 1026865.5
A9: Amortización de flujos de adquisición | B9: 108886.1 | C9: 0 | D9: 0 | E9: =SUM(B9:D9) -> 108886.1
A10: Pérdidas y reversiones en grupos onerosos | B10: 0 | C10: 217843.79 | D10: 0 | E10: =SUM(B10:D10) -> 217843.79
A11: Cambios del LIC por servicio pasado | B11: 0 | C11: 0 | D11: 315.9382 | E11: =SUM(B11:D11) -> 315.9382
A12: Componentes de inversión | B12: 0 | C12: 0 | D12: 0 | E12: =SUM(B12:D12) -> 0
A13: Ingresos o gastos financieros de seguros | B13: 14758.52 | C13: 71.110996 | D13: 0 | E13: =SUM(B13:D13) -> 14829.631
A14: Primas recibidas | B14: 3330340.9 | C14: 0 | D14: 0 | E14: =SUM(B14:D14) -> 3330340.9
A15: Siniestros y gastos pagados | B15: 0 | C15: 0 | D15: -963677.89 | E15: =SUM(B15:D15) -> -963677.89
A16: Flujos de adquisición pagados | B16: -2120728.7 | C16: 0 | D16: 0 | E16: =SUM(B16:D16) -> -2120728.7
A17: Saldo final | B17: =SUM(B6:B16) -> 144130.15 | C17: =SUM(C6:C16) -> 217914.9 | D17: =SUM(D6:D16) -> 63503.579 | E17: =SUM(E6:E16) -> 425548.63
A18: Control: saldo final de la fórmula - saldo del motor | B18: =B17-144130.150100621 -> 5.2386895e-10 | C18: =C17-217914.897137835 -> 0 | D18: =D17-63503.5789585253 -> 3.4197001e-10
A20: Vida temporal — 2024 | B20: LRC sin componente de pérdida | C20: Componente de pérdida | D20: LIC | E20: Total
A21: Saldo inicial | B21: =B17 -> 144130.15 | C21: =C17 -> 217914.9 | D21: =D17 -> 63503.579 | E21: =SUM(B21:D21) -> 425548.63
A22: Ingresos por seguros | B22: -3665183 | C22: 0 | D22: 0 | E22: =SUM(B22:D22) -> -3665183
A23: Siniestros y otros gastos incurridos | B23: 0 | C23: 0 | D23: 1961017.6 | E23: =SUM(B23:D23) -> 1961017.6
A24: Amortización de flujos de adquisición | B24: 300495.83 | C24: 0 | D24: 0 | E24: =SUM(B24:D24) -> 300495.83
A25: Pérdidas y reversiones en grupos onerosos | B25: 0 | C25: 645672.35 | D25: 0 | E25: =SUM(B25:D25) -> 645672.35
A26: Cambios del LIC por servicio pasado | B26: 0 | C26: 0 | D26: -61568.303 | E26: =SUM(B26:D26) -> -61568.303
A27: Componentes de inversión | B27: 0 | C27: 0 | D27: 0 | E27: =SUM(B27:D27) -> 0
A28: Ingresos o gastos financieros de seguros | B28: -125353.79 | C28: 519.55935 | D28: 0 | E28: =SUM(B28:D28) -> -124834.23
A29: Primas recibidas | B29: 6304236.5 | C29: 0 | D29: 0 | E29: =SUM(B29:D29) -> 6304236.5
A30: Siniestros y gastos pagados | B30: 0 | C30: 0 | D30: -1573962.3 | E30: =SUM(B30:D30) -> -1573962.3
A31: Flujos de adquisición pagados | B31: -2109882.6 | C31: 0 | D31: 0 | E31: =SUM(B31:D31) -> -2109882.6
A32: Saldo final | B32: =SUM(B21:B31) -> 848443.09 | C32: =SUM(C21:C31) -> 864106.8 | D32: =SUM(D21:D31) -> 388990.52 | E32: =SUM(E21:E31) -> 2101540.4
A33: Control: saldo final de la fórmula - saldo del motor | B33: =B32-848443.090026392 -> 0 | C33: =C32-864106.801529094 -> 0 | D33: =D32-388990.518563933 -> 0
A35: Vida temporal — 2025 | B35: LRC sin componente de pérdida | C35: Componente de pérdida | D35: LIC | E35: Total
A36: Saldo inicial | B36: =B32 -> 848443.09 | C36: =C32 -> 864106.8 | D36: =D32 -> 388990.52 | E36: =SUM(B36:D36) -> 2101540.4
A37: Ingresos por seguros | B37: -6126829.5 | C37: 0 | D37: 0 | E37: =SUM(B37:D37) -> -6126829.5
A38: Siniestros y otros gastos incurridos | B38: 0 | C38: 0 | D38: 4296058 | E38: =SUM(B38:D38) -> 4296058
A39: Amortización de flujos de adquisición | B39: 490841.3 | C39: 0 | D39: 0 | E39: =SUM(B39:D39) -> 490841.3
A40: Pérdidas y reversiones en grupos onerosos | B40: 0 | C40: -644767.29 | D40: 0 | E40: =SUM(B40:D40) -> -644767.29
A41: Cambios del LIC por servicio pasado | B41: 0 | C41: 0 | D41: 368389.41 | E41: =SUM(B41:D41) -> 368389.41
A42: Componentes de inversión | B42: 0 | C42: 0 | D42: 0 | E42: =SUM(B42:D42) -> 0
A43: Ingresos o gastos financieros de seguros | B43: -27468.105 | C43: 3213.5777 | D43: 0 | E43: =SUM(B43:D43) -> -24254.527
A44: Primas recibidas | B44: 9418139.3 | C44: 0 | D44: 0 | E44: =SUM(B44:D44) -> 9418139.3
A45: Siniestros y gastos pagados | B45: 0 | C45: 0 | D45: -4702294.3 | E45: =SUM(B45:D45) -> -4702294.3
A46: Flujos de adquisición pagados | B46: -2251768 | C46: 0 | D46: 0 | E46: =SUM(B46:D46) -> -2251768
A47: Saldo final | B47: =SUM(B36:B46) -> 2351358.1 | C47: =SUM(C36:C46) -> 222553.09 | D47: =SUM(D36:D46) -> 351143.62 | E47: =SUM(E36:E46) -> 2925054.8
A48: Control: saldo final de la fórmula - saldo del motor | B48: =B47-2351358.10224247 -> 0 | C48: =C47-222553.085087743 -> 0 | D48: =D47-351143.616689957 -> 0
A51: Vida con ahorro
A52: Vida con ahorro — 2023 | B52: LRC sin componente de pérdida | C52: Componente de pérdida | D52: LIC | E52: Total
A53: Saldo inicial | B53: 0 | C53: 0 | D53: 0 | E53: =SUM(B53:D53) -> 0
A54: Ingresos por seguros | B54: -345056.34 | C54: 0 | D54: 0 | E54: =SUM(B54:D54) -> -345056.34
A55: Siniestros y otros gastos incurridos | B55: 0 | C55: 0 | D55: 169577.54 | E55: =SUM(B55:D55) -> 169577.54
A56: Amortización de flujos de adquisición | B56: 150431.17 | C56: 0 | D56: 0 | E56: =SUM(B56:D56) -> 150431.17
A57: Pérdidas y reversiones en grupos onerosos | B57: 0 | C57: 0 | D57: 0 | E57: =SUM(B57:D57) -> 0
A58: Cambios del LIC por servicio pasado | B58: 0 | C58: 0 | D58: 22.404842 | E58: =SUM(B58:D58) -> 22.404842
A59: Componentes de inversión | B59: -200203.99 | C59: 0 | D59: 200203.99 | E59: =SUM(B59:D59) -> 0
A60: Ingresos o gastos financieros de seguros | B60: -58978.643 | C60: 0 | D60: 0 | E60: =SUM(B60:D60) -> -58978.643
A61: Primas recibidas | B61: 4518410 | C61: 0 | D61: 0 | E61: =SUM(B61:D61) -> 4518410
A62: Siniestros y gastos pagados | B62: 0 | C62: 0 | D62: -365300.56 | E62: =SUM(B62:D62) -> -365300.56
A63: Flujos de adquisición pagados | B63: -1987549.6 | C63: 0 | D63: 0 | E63: =SUM(B63:D63) -> -1987549.6
A64: Saldo final | B64: =SUM(B53:B63) -> 2077052.6 | C64: =SUM(C53:C63) -> 0 | D64: =SUM(D53:D63) -> 4503.3732 | E64: =SUM(E53:E63) -> 2081556
A65: Control: saldo final de la fórmula - saldo del motor | B65: =B64-2077052.62212537 -> 0 | C65: =C64-0 -> 0 | D65: =D64-4503.37317272192 -> -1.0641088e-10
A67: Vida con ahorro — 2024 | B67: LRC sin componente de pérdida | C67: Componente de pérdida | D67: LIC | E67: Total
A68: Saldo inicial | B68: =B64 -> 2077052.6 | C68: =C64 -> 0 | D68: =D64 -> 4503.3732 | E68: =SUM(B68:D68) -> 2081556
A69: Ingresos por seguros | B69: -1059046 | C69: 0 | D69: 0 | E69: =SUM(B69:D69) -> -1059046
A70: Siniestros y otros gastos incurridos | B70: 0 | C70: 0 | D70: 465010.95 | E70: =SUM(B70:D70) -> 465010.95
A71: Amortización de flujos de adquisición | B71: 297391.42 | C71: 0 | D71: 0 | E71: =SUM(B71:D71) -> 297391.42
A72: Pérdidas y reversiones en grupos onerosos | B72: 0 | C72: 0 | D72: 0 | E72: =SUM(B72:D72) -> 0
A73: Cambios del LIC por servicio pasado | B73: 0 | C73: 0 | D73: -4458.0907 | E73: =SUM(B73:D73) -> -4458.0907
A74: Componentes de inversión | B74: -573578.44 | C74: 0 | D74: 573578.44 | E74: =SUM(B74:D74) -> 0
A75: Ingresos o gastos financieros de seguros | B75: 364240.99 | C75: 0 | D75: 0 | E75: =SUM(B75:D75) -> 364240.99
A76: Primas recibidas | B76: 8583370 | C76: 0 | D76: 0 | E76: =SUM(B76:D76) -> 8583370
A77: Siniestros y gastos pagados | B77: 0 | C77: 0 | D77: -1029532.9 | E77: =SUM(B77:D77) -> -1029532.9
A78: Flujos de adquisición pagados | B78: -1976308.8 | C78: 0 | D78: 0 | E78: =SUM(B78:D78) -> -1976308.8
A79: Saldo final | B79: =SUM(B68:B78) -> 7713121.7 | C79: =SUM(C68:C78) -> 0 | D79: =SUM(D68:D78) -> 9101.7854 | E79: =SUM(E68:E78) -> 7722223.5
A80: Control: saldo final de la fórmula - saldo del motor | B80: =B79-7713121.74668131 -> 0 | C80: =C79-0 -> 0 | D80: =D79-9101.78542057975 -> -3.0377123e-10
A82: Vida con ahorro — 2025 | B82: LRC sin componente de pérdida | C82: Componente de pérdida | D82: LIC | E82: Total
A83: Saldo inicial | B83: =B79 -> 7713121.7 | C83: =C79 -> 0 | D83: =D79 -> 9101.7854 | E83: =SUM(B83:D83) -> 7722223.5
A84: Ingresos por seguros | B84: -1498832.8 | C84: 0 | D84: 0 | E84: =SUM(B84:D84) -> -1498832.8
A85: Siniestros y otros gastos incurridos | B85: 0 | C85: 0 | D85: 898790.22 | E85: =SUM(B85:D85) -> 898790.22
A86: Amortización de flujos de adquisición | B86: 441716.23 | C86: 0 | D86: 0 | E86: =SUM(B86:D86) -> 441716.23
A87: Pérdidas y reversiones en grupos onerosos | B87: 0 | C87: 0 | D87: 0 | E87: =SUM(B87:D87) -> 0
A88: Cambios del LIC por servicio pasado | B88: 0 | C88: 0 | D88: -9037.058 | E88: =SUM(B88:D88) -> -9037.058
A89: Componentes de inversión | B89: -1421061.5 | C89: 0 | D89: 1421061.5 | E89: =SUM(B89:D89) -> 0
A90: Ingresos o gastos financieros de seguros | B90: 103997.01 | C90: 0 | D90: 0 | E90: =SUM(B90:D90) -> 103997.01
A91: Primas recibidas | B91: 12303580 | C91: 0 | D91: 0 | E91: =SUM(B91:D91) -> 12303580
A92: Siniestros y gastos pagados | B92: 0 | C92: 0 | D92: -2306906.2 | E92: =SUM(B92:D92) -> -2306906.2
A93: Flujos de adquisición pagados | B93: -1965802.5 | C93: 0 | D93: 0 | E93: =SUM(B93:D93) -> -1965802.5
A94: Saldo final | B94: =SUM(B83:B93) -> 15676718 | C94: =SUM(C83:C93) -> 0 | D94: =SUM(D83:D93) -> 13010.22 | E94: =SUM(E83:E93) -> 15689728
A95: Control: saldo final de la fórmula - saldo del motor | B95: =B94-15676718.1538939 -> 0 | C95: =C94-0 -> 0 | D95: =D94-13010.2198674482 -> -5.657057e-10
A98: Autos
A99: Autos — 2023 | B99: LRC sin componente de pérdida | C99: Componente de pérdida | D99: LIC | E99: Total
A100: Saldo inicial | B100: 0 | C100: 0 | D100: 0 | E100: =SUM(B100:D100) -> 0
A101: Ingresos por seguros | B101: -6125951.6 | C101: 0 | D101: 0 | E101: =SUM(B101:D101) -> -6125951.6
A102: Siniestros y otros gastos incurridos | B102: 0 | C102: 0 | D102: 4486975.5 | E102: =SUM(B102:D102) -> 4486975.5
A103: Amortización de flujos de adquisición | B103: 918892.74 | C103: 0 | D103: 0 | E103: =SUM(B103:D103) -> 918892.74
A104: Pérdidas y reversiones en grupos onerosos | B104: 0 | C104: 0 | D104: 0 | E104: =SUM(B104:D104) -> 0
A105: Cambios del LIC por servicio pasado | B105: 0 | C105: 0 | D105: 255555.63 | E105: =SUM(B105:D105) -> 255555.63
A106: Componentes de inversión | B106: 0 | C106: 0 | D106: 0 | E106: =SUM(B106:D106) -> 0
A107: Ingresos o gastos financieros de seguros | B107: 0 | C107: 0 | D107: 0 | E107: =SUM(B107:D107) -> 0
A108: Primas recibidas | B108: 10813562 | C108: 0 | D108: 0 | E108: =SUM(B108:D108) -> 10813562
A109: Siniestros y gastos pagados | B109: 0 | C109: 0 | D109: -1983294.6 | E109: =SUM(B109:D109) -> -1983294.6
...

Sheet Conc_101
A1: Conciliación del valor presente de los flujos, el ajuste por riesgo y el CSM (par. 101, 104)
A2: Contratos medidos con el GMM. El reaseguro cedido se muestra como activo (signo positivo) y por separado (par. 98).
A4: Vida temporal
A5: Vida temporal — 2023 | B5: Valor presente de flujos futuros | C5: Ajuste por riesgo no financiero | D5: Margen contractual de servicio | E5: Total
A6: Saldo inicial | B6: 0 | C6: 0 | D6: 0 | E6: =SUM(B6:D6) -> 0
A7: Cambios en estimaciones que ajustan el CSM | B7: 320955.88 | C7: 17259.844 | D7: -338215.72 | E7: =SUM(B7:D7) -> 0
A8: Cambios que no ajustan el CSM (onerosos) | B8: 57414.146 | C8: 4482.5578 | D8: 0 | E8: =SUM(B8:D8) -> 61896.704
A9: Recuperación de pérdidas (reaseguro, 66A) | B9: 0 | C9: 0 | D9: 0 | E9: =SUM(B9:D9) -> 0
A10: Contratos reconocidos en el periodo | B10: -4164573.5 | C10: 1210744.3 | D10: 3117508.9 | E10: =SUM(B10:D10) -> 163679.61
A11: CSM reconocido por servicios | B11: 0 | C11: 0 | D11: -144388.95 | E11: =SUM(B11:D11) -> -144388.95
A12: Cambio del ajuste por riesgo por riesgo vencido | B12: 0 | C12: -2541.8914 | D12: 0 | E12: =SUM(B12:D12) -> -2541.8914
A13: Ajustes por experiencia | B13: 85823.223 | C13: 0 | D13: 0 | E13: =SUM(B13:D13) -> 85823.223
A14: Ingresos o gastos financieros de seguros | B14: -76281.167 | C14: 0 | D14: 91110.798 | E14: =SUM(B14:D14) -> 14829.631
A15: Primas recibidas / pagadas | B15: 3330340.9 | C15: 0 | D15: 0 | E15: =SUM(B15:D15) -> 3330340.9
A16: Siniestros y gastos incurridos / recuperaciones | B16: -1026865.5 | C16: 0 | D16: 0 | E16: =SUM(B16:D16) -> -1026865.5
A17: Componentes de inversión | B17: 0 | C17: 0 | D17: 0 | E17: =SUM(B17:D17) -> 0
A18: Flujos de adquisición pagados | B18: -2120728.7 | C18: 0 | D18: 0 | E18: =SUM(B18:D18) -> -2120728.7
A19: Saldo final | B19: =SUM(B6:B18) -> -3593914.7 | C19: =SUM(C6:C18) -> 1229944.8 | D19: =SUM(D6:D18) -> 2726015 | E19: =SUM(E6:E18) -> 362045.05
A20: Control: saldo final de la fórmula - saldo del motor | B20: =B19--3593914.74723631 -> 0 | C20: =C19-1229944.8094988 -> 0 | D20: =D19-2726014.98497596 -> 0
A22: Vida temporal — 2024 | B22: Valor presente de flujos futuros | C22: Ajuste por riesgo no financiero | D22: Margen contractual de servicio | E22: Total
A23: Saldo inicial | B23: =B19 -> -3593914.7 | C23: =C19 -> 1229944.8 | D23: =D19 -> 2726015 | E23: =SUM(B23:D23) -> 362045.05
A24: Cambios en estimaciones que ajustan el CSM | B24: 695871.31 | C24: 44478.291 | D24: -740349.6 | E24: =SUM(B24:D24) -> 0
A25: Cambios que no ajustan el CSM (onerosos) | B25: 494066.72 | C25: 27820.115 | D25: 0 | E25: =SUM(B25:D25) -> 521886.84
A26: Recuperación de pérdidas (reaseguro, 66A) | B26: 0 | C26: 0 | D26: 0 | E26: =SUM(B26:D26) -> 0
A27: Contratos reconocidos en el periodo | B27: -4020735.1 | C27: 1231288.8 | D27: 2940782.7 | E27: =SUM(B27:D27) -> 151336.34
A28: CSM reconocido por servicios | B28: 0 | C28: 0 | D28: -365540.56 | E28: =SUM(B28:D28) -> -365540.56
A29: Cambio del ajuste por riesgo por riesgo vencido | B29: 0 | C29: -216542.84 | D29: 0 | E29: =SUM(B29:D29) -> -216542.84
A30: Ajustes por experiencia | B30: -849137.05 | C30: 0 | D30: 0 | E30: =SUM(B30:D30) -> -849137.05
A31: Ingresos o gastos financieros de seguros | B31: -349291.01 | C31: 0 | D31: 224456.78 | E31: =SUM(B31:D31) -> -124834.23
A32: Primas recibidas / pagadas | B32: 6304236.5 | C32: 0 | D32: 0 | E32: =SUM(B32:D32) -> 6304236.5
A33: Siniestros y gastos incurridos / recuperaciones | B33: -1961017.6 | C33: 0 | D33: 0 | E33: =SUM(B33:D33) -> -1961017.6
A34: Componentes de inversión | B34: 0 | C34: 0 | D34: 0 | E34: =SUM(B34:D34) -> 0
A35: Flujos de adquisición pagados | B35: -2109882.6 | C35: 0 | D35: 0 | E35: =SUM(B35:D35) -> -2109882.6
A36: Saldo final | B36: =SUM(B23:B35) -> -5389803.5 | C36: =SUM(C23:C35) -> 2316989.1 | D36: =SUM(D23:D35) -> 4785364.3 | E36: =SUM(E23:E35) -> 1712549.9
A37: Control: saldo final de la fórmula - saldo del motor | B37: =B36--5389803.49147336 -> 0 | C37: =C36-2316989.13124314 -> 0 | D37: =D36-4785364.25178571 -> 0
A39: Vida temporal — 2025 | B39: Valor presente de flujos futuros | C39: Ajuste por riesgo no financiero | D39: Margen contractual de servicio | E39: Total
A40: Saldo inicial | B40: =B36 -> -5389803.5 | C40: =C36 -> 2316989.1 | D40: =D36 -> 4785364.3 | E40: =SUM(B40:D40) -> 1712549.9
A41: Cambios en estimaciones que ajustan el CSM | B41: -2251074.1 | C41: -105580.53 | D41: 2356654.7 | E41: =SUM(B41:D41) -> 0
A42: Cambios que no ajustan el CSM (onerosos) | B42: -532040.79 | C42: -33433.07 | D42: 0 | E42: =SUM(B42:D42) -> -565473.86
A43: Recuperación de pérdidas (reaseguro, 66A) | B43: 0 | C43: 0 | D43: 0 | E43: =SUM(B43:D43) -> 0
A44: Contratos reconocidos en el periodo | B44: -5534701.1 | C44: 1279700.1 | D44: 4255001 | E44: =SUM(B44:D44) -> 0
A45: CSM reconocido por servicios | B45: 0 | C45: 0 | D45: -897245.39 | E45: =SUM(B45:D45) -> -897245.39
A46: Cambio del ajuste por riesgo por riesgo vencido | B46: 0 | C46: -44458.571 | D46: 0 | E46: =SUM(B46:D46) -> -44458.571
A47: Ajustes por experiencia | B47: -477519.72 | C47: 0 | D47: 0 | E47: =SUM(B47:D47) -> -477519.72
A48: Ingresos o gastos financieros de seguros | B48: -360700.18 | C48: 0 | D48: 336445.65 | E48: =SUM(B48:D48) -> -24254.527
A49: Primas recibidas / pagadas | B49: 9418139.3 | C49: 0 | D49: 0 | E49: =SUM(B49:D49) -> 9418139.3
A50: Siniestros y gastos incurridos / recuperaciones | B50: -4296058 | C50: 0 | D50: 0 | E50: =SUM(B50:D50) -> -4296058
A51: Componentes de inversión | B51: 0 | C51: 0 | D51: 0 | E51: =SUM(B51:D51) -> 0
A52: Flujos de adquisición pagados | B52: -2251768 | C52: 0 | D52: 0 | E52: =SUM(B52:D52) -> -2251768
A53: Saldo final | B53: =SUM(B40:B52) -> -11675526 | C53: =SUM(C40:C52) -> 3413217 | D53: =SUM(D40:D52) -> 10836220 | E53: =SUM(E40:E52) -> 2573911.2
A54: Control: saldo final de la fórmula - saldo del motor | B54: =B53--11675526.0445088 -> 0 | C54: =C53-3413217.04782715 -> 0 | D54: =D53-10836220.1840118 -> 0
A57: Vida con ahorro
A58: Vida con ahorro — 2023 | B58: Valor presente de flujos futuros | C58: Ajuste por riesgo no financiero | D58: Margen contractual de servicio | E58: Total
A59: Saldo inicial | B59: 0 | C59: 0 | D59: 0 | E59: =SUM(B59:D59) -> 0
A60: Cambios en estimaciones que ajustan el CSM | B60: 21621.306 | C60: -6149.1551 | D60: -15472.151 | E60: =SUM(B60:D60) -> 0
A61: Cambios que no ajustan el CSM (onerosos) | B61: 0 | C61: 0 | D61: 0 | E61: =SUM(B61:D61) -> 0
A62: Recuperación de pérdidas (reaseguro, 66A) | B62: 0 | C62: 0 | D62: 0 | E62: =SUM(B62:D62) -> 0
A63: Contratos reconocidos en el periodo | B63: -3015983.6 | C63: 772192.83 | D63: 2243790.7 | E63: =SUM(B63:D63) -> 0
A64: CSM reconocido por servicios | B64: 0 | C64: 0 | D64: -18642.239 | E64: =SUM(B64:D64) -> -18642.239
A65: Cambio del ajuste por riesgo por riesgo vencido | B65: 0 | C65: 23872.702 | D65: 0 | E65: =SUM(B65:D65) -> 23872.702
A66: Ajustes por experiencia | B66: -30278.089 | C66: 0 | D66: 0 | E66: =SUM(B66:D66) -> -30278.089
A67: Ingresos o gastos financieros de seguros | B67: -127580.54 | C67: 0 | D67: 68601.901 | E67: =SUM(B67:D67) -> -58978.643
A68: Primas recibidas / pagadas | B68: 4518410 | C68: 0 | D68: 0 | E68: =SUM(B68:D68) -> 4518410
A69: Siniestros y gastos incurridos / recuperaciones | B69: -169577.54 | C69: 0 | D69: 0 | E69: =SUM(B69:D69) -> -169577.54
A70: Componentes de inversión | B70: -200203.99 | C70: 0 | D70: 0 | E70: =SUM(B70:D70) -> -200203.99
A71: Flujos de adquisición pagados | B71: -1987549.6 | C71: 0 | D71: 0 | E71: =SUM(B71:D71) -> -1987549.6
A72: Saldo final | B72: =SUM(B59:B71) -> -991141.99 | C72: =SUM(C59:C71) -> 789916.38 | D72: =SUM(D59:D71) -> 2278278.2 | E72: =SUM(E59:E71) -> 2077052.6
A73: Control: saldo final de la fórmula - saldo del motor | B73: =B72--991141.990608482 -> 0 | C73: =C72-789916.37723796 -> 0 | D73: =D72-2278278.2354959 -> 0
A75: Vida con ahorro — 2024 | B75: Valor presente de flujos futuros | C75: Ajuste por riesgo no financiero | D75: Margen contractual de servicio | E75: Total
A76: Saldo inicial | B76: =B72 -> -991141.99 | C76: =C72 -> 789916.38 | D76: =D72 -> 2278278.2 | E76: =SUM(B76:D76) -> 2077052.6
A77: Cambios en estimaciones que ajustan el CSM | B77: -221428.35 | C77: 11741.034 | D77: 209687.32 | E77: =SUM(B77:D77) -> 0
A78: Cambios que no ajustan el CSM (onerosos) | B78: 0 | C78: 0 | D78: 0 | E78: =SUM(B78:D78) -> 0
A79: Recuperación de pérdidas (reaseguro, 66A) | B79: 0 | C79: 0 | D79: 0 | E79: =SUM(B79:D79) -> 0
A80: Contratos reconocidos en el periodo | B80: -2902125.8 | C80: 773206.31 | D80: 2128919.5 | E80: =SUM(B80:D80) -> 0
A81: CSM reconocido por servicios | B81: 0 | C81: 0 | D81: -56118.692 | E81: =SUM(B81:D81) -> -56118.692
A82: Cambio del ajuste por riesgo por riesgo vencido | B82: 0 | C82: -108105.06 | D82: 0 | E82: =SUM(B82:D82) -> -108105.06
A83: Ajustes por experiencia | B83: -132419.91 | C83: 0 | D83: 0 | E83: =SUM(B83:D83) -> -132419.91
A84: Ingresos o gastos financieros de seguros | B84: 184543.71 | C84: 0 | D84: 179697.29 | E84: =SUM(B84:D84) -> 364240.99
A85: Primas recibidas / pagadas | B85: 8583370 | C85: 0 | D85: 0 | E85: =SUM(B85:D85) -> 8583370
A86: Siniestros y gastos incurridos / recuperaciones | B86: -465010.95 | C86: 0 | D86: 0 | E86: =SUM(B86:D86) -> -465010.95
A87: Componentes de inversión | B87: -573578.44 | C87: 0 | D87: 0 | E87: =SUM(B87:D87) -> -573578.44
A88: Flujos de adquisición pagados | B88: -1976308.8 | C88: 0 | D88: 0 | E88: =SUM(B88:D88) -> -1976308.8
A89: Saldo final | B89: =SUM(B76:B88) -> 1505899.5 | C89: =SUM(C76:C88) -> 1466758.7 | D89: =SUM(D76:D88) -> 4740463.6 | E89: =SUM(E76:E88) -> 7713121.7
A90: Control: saldo final de la fórmula - saldo del motor | B90: =B89-1505899.48219972 -> 0 | C90: =C89-1466758.66140501 -> 0 | D90: =D89-4740463.60307658 -> 0
A92: Vida con ahorro — 2025 | B92: Valor presente de flujos futuros | C92: Ajuste por riesgo no financiero | D92: Margen contractual de servicio | E92: Total
A93: Saldo inicial | B93: =B89 -> 1505899.5 | C93: =C89 -> 1466758.7 | D93: =D89 -> 4740463.6 | E93: =SUM(B93:D93) -> 7713121.7
A94: Cambios en estimaciones que ajustan el CSM | B94: -81205.311 | C94: 6979.2739 | D94: 74226.037 | E94: =SUM(B94:D94) -> 0
A95: Cambios que no ajustan el CSM (onerosos) | B95: 0 | C95: 0 | D95: 0 | E95: =SUM(B95:D95) -> 0
A96: Recuperación de pérdidas (reaseguro, 66A) | B96: 0 | C96: 0 | D96: 0 | E96: =SUM(B96:D96) -> 0
A97: Contratos reconocidos en el periodo | B97: -2855228.9 | C97: 767372.67 | D97: 2087856.3 | E97: =SUM(B97:D97) -> 0
A98: CSM reconocido por servicios | B98: 0 | C98: 0 | D98: -100439.22 | E98: =SUM(B98:D98) -> -100439.22
A99: Cambio del ajuste por riesgo por riesgo vencido | B99: 0 | C99: 11388.897 | D99: 0 | E99: =SUM(B99:D99) -> 11388.897
A100: Ajustes por experiencia | B100: -69276.033 | C100: 0 | D100: 0 | E100: =SUM(B100:D100) -> -69276.033
A101: Ingresos o gastos financieros de seguros | B101: -178301.69 | C101: 0 | D101: 282298.69 | E101: =SUM(B101:D101) -> 103997.01
A102: Primas recibidas / pagadas | B102: 12303580 | C102: 0 | D102: 0 | E102: =SUM(B102:D102) -> 12303580
A103: Siniestros y gastos incurridos / recuperaciones | B103: -898790.22 | C103: 0 | D103: 0 | E103: =SUM(B103:D103) -> -898790.22
A104: Componentes de inversión | B104: -1421061.5 | C104: 0 | D104: 0 | E104: =SUM(B104:D104) -> -1421061.5
A105: Flujos de adquisición pagados | B105: -1965802.5 | C105: 0 | D105: 0 | E105: =SUM(B105:D105) -> -1965802.5
A106: Saldo final | B106: =SUM(B93:B105) -> 6339813.3 | C106: =SUM(C93:C105) -> 2252499.5 | D106: =SUM(D93:D105) -> 7084405.4 | E106: =SUM(E93:E105) -> 15676718
A107: Control: saldo final de la fórmula - saldo del motor | B107: =B106-6339813.28374537 -> 0 | C107: =C106-2252499.50628073 -> 0 | D107: =D106-7084405.36386779 -> 0
...

Sheet Ingresos_106
A1: Análisis de los ingresos por seguros, grupos GMM (par. 106)
A2: Siniestros y gastos esperados, liberación del ajuste por riesgo y del CSM, y recuperación de adquisición (B121-B125).
A4: closing | B4: portfolio | C4: expected_claims_and_expenses | D4: loss_component_exclusion | E4: ra_release | F4: csm_release | G4: acquisition_recovery | H4: insurance_revenue | I4: Total por fórmula
A5: 2023-12-31 | B5: VA | C5: 199855.63 | D5: 0 | E5: -23872.702 | F5: 18642.239 | G5: 150431.17 | H5: 345056.34 | I5: =SUM(C5:G5) -> 345056.34 | J5: =I5-H5 -> 0
A6: 2023-12-31 | B6: VT | C6: 941042.31 | D6: -7732.5257 | E6: 2541.8914 | F6: 144388.95 | G6: 108886.1 | H6: 1189126.7 | I6: =SUM(C6:G6) -> 1189126.7 | J6: =I6-H6 -> 0
A7: 2024-12-31 | B7: VA | C7: 597430.86 | D7: 0 | E7: 108105.06 | F7: 56118.692 | G7: 297391.42 | H7: 1059046 | I7: =SUM(C7:G7) -> 1059046 | J7: =I7-H7 -> 0
A8: 2024-12-31 | B8: VT | C8: 2810154.6 | D8: -27550.836 | E8: 216542.84 | F8: 365540.56 | G8: 300495.83 | H8: 3665183 | I8: =SUM(C8:G8) -> 3665183 | J8: =I8-H8 -> 0
A9: 2025-12-31 | B9: VA | C9: 968066.26 | D9: 0 | E9: -11388.897 | F9: 100439.22 | G9: 441716.23 | H9: 1498832.8 | I9: =SUM(C9:G9) -> 1498832.8 | J9: =I9-H9 -> 0
A10: 2025-12-31 | B10: VT | C10: 4773577.7 | D10: -79293.436 | E10: 44458.571 | F10: 897245.39 | G10: 490841.3 | H10: 6126829.5 | I10: =SUM(C10:G10) -> 6126829.5 | J10: =I10-H10 -> 0
A11: Control: total por fórmula - ingresos del motor

Sheet NegocioNuevo_107
A1: Contratos reconocidos en el periodo (par. 107)
A2: Salidas (con adquisición aparte), entradas, ajuste por riesgo y CSM; los grupos onerosos van aparte. La suma es la pérdida inicial.
A4: closing | B4: portfolio | C4: onerous | D4: pv_acquisition_outflows | E4: pv_other_outflows | F4: pv_inflows | G4: ra | H4: csm | I4: loss | J4: Suma = pérdida | K4: Control: suma - pérdida
A5: 2023-12-31 | B5: VA | C5: =FALSE() -> FALSE | D5: 1987549.6 | E5: 33190296 | F5: -38193830 | G5: 772192.83 | H5: 2243790.7 | I5: 0 | J5: =SUM(D5:H5) -> 1.0244548e-08 | K5: =J5-I5 -> 1.0244548e-08
A6: 2023-12-31 | B6: VT | C6: =FALSE() -> FALSE | D6: 1853044.4 | E6: 16733824 | F6: -22736501 | G6: 1032123.3 | H6: 3117508.9 | I6: 0 | J6: =SUM(D6:H6) -> 0 | K6: =J6-I6 -> 0
A7: 2023-12-31 | B7: VT | C7: =TRUE() -> TRUE | D7: 267684.25 | E7: 2872075.6 | F7: -3154701.3 | G7: 178621.03 | H7: 0 | I7: 163679.61 | J7: =SUM(D7:H7) -> 163679.61 | K7: =J7-I7 -> 0
A8: 2024-12-31 | B8: VA | C8: =FALSE() -> FALSE | D8: 1976308.8 | E8: 33191215 | F8: -38069649 | G8: 773206.31 | H8: 2128919.5 | I8: 0 | J8: =SUM(D8:H8) -> 0 | K8: =J8-I8 -> 0
A9: 2024-12-31 | B9: VT | C9: =FALSE() -> FALSE | D9: 1864574.9 | E9: 17110707 | F9: -22984741 | G9: 1068676.5 | H9: 2940782.7 | I9: 0 | J9: =SUM(D9:H9) -> 0 | K9: =J9-I9 -> 0
A10: 2024-12-31 | B10: VT | C10: =TRUE() -> TRUE | D10: 245307.69 | E10: 2578273.9 | F10: -2834857.6 | G10: 162612.27 | H10: 0 | I10: 151336.34 | J10: =SUM(D10:H10) -> 151336.34 | K10: =J10-I10 -> 0
A11: 2025-12-31 | B11: VA | C11: =FALSE() -> FALSE | D11: 1965802.5 | E11: 32973789 | F11: -37794820 | G11: 767372.67 | H11: 2087856.3 | I11: 0 | J11: =SUM(D11:H11) -> 0 | K11: =J11-I11 -> 0
A12: 2025-12-31 | B12: VT | C12: =FALSE() -> FALSE | D12: 2251768 | E12: 20295053 | F12: -28081522 | G12: 1279700.1 | H12: 4255001 | I12: 0 | J12: =SUM(D12:H12) -> 0 | K12: =J12-I12 -> 0

Sheet CSM_109
A1: Reconocimiento esperado del CSM al 31-dic-2025 (par. 109)
A2: Años en que se espera reconocer el CSM según las unidades de cobertura futuras, sin acreción futura. El reaseguro se muestra con signo de costo (negativo).
A4: portfolio | B4: 1 | C4: 2 | D4: 3 | E4: 4 | F4: 5 | G4: 6-10 | H4: >10 | I4: Total
A5: VT | B5: 1072955.2 | C5: 1009117.9 | D5: 961013.32 | E5: 919008.13 | F5: 878603.69 | G5: 3535818.8 | H5: 2459703.2 | I5: =SUM(B5:H5) -> 10836220
A6: RE_VT | B6: -393574.4 | C6: -370267.43 | D6: -352713.3 | E6: -337393.7 | F6: -322659.85 | G6: -1301621.4 | H6: -939261.36 | I6: =SUM(B6:H6) -> -4017491.4
A7: VA | B7: 126562.23 | C7: 141819.87 | D7: 156597.49 | E7: 170293.59 | F7: 184008.14 | G7: 1137020 | H7: 5168104 | I7: =SUM(B7:H7) -> 7084405.4

Sheet Supuestos
A1: Supuestos, curvas y nivel de confianza (par. 117, 119, 120)
A2: Factores de mortalidad por cierre, curvas spot (anual efectiva) y nivel de confianza.
A4: Supuestos
A5: closing | B5: assumption | C5: value | D5: basis | E5: own_factor | F5: credibility
A6: 2023-12-31 | B6: mortalidad (default) | C6: 0.7714629655051102 | D6: factor sobre CSO 1980 | E6: 1.0382224 | F6: 0.074466681
A7: 2023-12-31 | B7: mortalidad (older_high_si) | C7: 0.75 | D7: factor sobre CSO 1980 | E7: 0 | F7: 0
A8: 2024-12-31 | B8: mortalidad (default) | C8: 0.7475383180864552 | D8: factor sobre CSO 1980 | E8: 0.7297565 | F8: 0.12160358
A9: 2024-12-31 | B9: mortalidad (older_high_si) | C9: 1.15 | D9: factor sobre CSO 1980 | E9: 0 | F9: 0
A10: 2025-12-31 | B10: mortalidad (default) | C10: 0.7379584723545553 | D10: factor sobre CSO 1980 | E10: 0.68104937 | F10: 0.17463985
A11: 2025-12-31 | B11: mortalidad (older_high_si) | C11: 0.8515890474076682 | D11: factor sobre CSO 1980 | E11: 0.88017796 | F11: 0.052655895
A12: todos | B12: mejora de mortalidad | C12: 0.01 | D12: anual
A13: todos | B13: caducidad vida temporal (años 1, 2, 3+) | C13: (0.08, 0.06, 0.04) | D13: anual
A14: todos | B14: caducidad vida con ahorro (años 1-7+) | C14: (0.1, 0.08, 0.07, 0.06, 0.05, 0.07, 0.04) | D14: anual
A15: todos | B15: inflación de gastos | C15: 0.025 | D15: anual
A16: todos | B16: diferencial de tasa acreditada | C16: 0.0125 | D16: HQM a 1 año menos diferencial, mínimo 2,5% (B98)
A19: Curvas de descuento (spot anual)
A20: closing | B20: portfolio | C20: 1y | D20: 5y | E20: 10y | F20: 20y | G20: 30y | H20: 40y
A21: 2023-12-31 | B21: VT | C21: 0.051855 | D21: 0.046324 | E21: 0.049703 | F21: 0.051753 | G21: 0.05165 | H21: 0.05165
A22: 2023-12-31 | B22: VA | C22: 0.051855 | D22: 0.046324 | E22: 0.049703 | F22: 0.051753 | G22: 0.05165 | H22: 0.05165
A23: 2023-12-31 | B23: AUTO | C23: 0.051855 | D23: 0.046324 | E23: 0.049703 | F23: 0.051753 | G23: 0.05165 | H23: 0.05165
A24: 2023-12-31 | B24: TRC | C24: 0.051855 | D24: 0.046324 | E24: 0.049703 | F24: 0.051753 | G24: 0.05165 | H24: 0.05165
A25: 2024-12-31 | B25: VT | C25: 0.046427 | D25: 0.0496 | E25: 0.054318 | F25: 0.058429 | G25: 0.058738 | H25: 0.059356
A26: 2024-12-31 | B26: VA | C26: 0.046427 | D26: 0.0496 | E26: 0.054318 | F26: 0.058429 | G26: 0.058738 | H26: 0.059356
A27: 2024-12-31 | B27: AUTO | C27: 0.046427 | D27: 0.0496 | E27: 0.054318 | F27: 0.058429 | G27: 0.058738 | H27: 0.059356
A28: 2024-12-31 | B28: TRC | C28: 0.046427 | D28: 0.0496 | E28: 0.054318 | F28: 0.058429 | G28: 0.058738 | H28: 0.059356
A29: 2025-12-31 | B29: VT | C29: 0.038769 | D29: 0.042952 | E29: 0.050215 | F29: 0.058429 | G29: 0.061312 | H29: 0.062858
A30: 2025-12-31 | B30: VA | C30: 0.038769 | D30: 0.042952 | E30: 0.050215 | F30: 0.058429 | G30: 0.061312 | H30: 0.062858
A31: 2025-12-31 | B31: AUTO | C31: 0.038769 | D31: 0.042952 | E31: 0.050215 | F31: 0.058429 | G31: 0.061312 | H31: 0.062858
A32: 2025-12-31 | B32: TRC | C32: 0.038769 | D32: 0.042952 | E32: 0.050215 | F32: 0.058429 | G32: 0.061312 | H32: 0.062858
A35: Nivel de confianza del ajuste por riesgo
A36: portfolio | B36: technique | C36: risk_adjustment | D36: capital_99_5 | E36: confidence_level
A37: Vida temporal | B37: costo de capital 6% | C37: 3413217 | D37: 7491576 | E37: 0.8797157
A38: Daños (LIC) | B38: percentil 75, lognormal, correlación 25% | C38: 769958.27 | E38: 0.7326508

Sheet Sensibilidades_128
A1: Sensibilidades al 31-dic-2025 (par. 128(a))
A2: Efecto en resultados y patrimonio, bruto y neto de reaseguro. Los cambios no financieros que absorbe el CSM no afectan el resultado.
A4: portfolio | B4: change | C4: profit_gross | D4: equity_gross | E4: profit_net | F4: equity_net
A5: VT | B5: mortalidad +10% | C5: -470262.99 | D5: -470262.99 | E5: -282157.8 | F5: -282157.8
A6: VT | B6: mortalidad -10% | C6: 222553.09 | D6: 222553.09 | E6: 133531.85 | F6: 133531.85
A7: VT | B7: caducidad +10% | C7: 19154.621 | D7: 19154.621 | E7: 19154.621 | F7: 19154.621
A8: VT | B8: caducidad -10% | C8: -20327.389 | D8: -20327.389 | E8: -20327.389 | F8: -20327.389
A9: VT | B9: gastos +10% | C9: -27723.12 | D9: -27723.12 | E9: -27723.12 | F9: -27723.12
A10: VT | B10: tasas +100 pb | C10: 0 | D10: 48767.651 | E10: 0 | F10: 29260.59
A11: VT | B11: tasas -100 pb | C11: 0 | D11: -97195.453 | E11: 0 | F11: -58317.272
A12: VA | B12: mortalidad +10% | C12: 0 | D12: 0 | E12: 0 | F12: 0
A13: VA | B13: caducidad +10% | C13: 0 | D13: 0 | E13: 0 | F13: 0
A14: VA | B14: caducidad -10% | C14: 0 | D14: 0 | E14: 0 | F14: 0
A15: VA | B15: gastos +10% | C15: 0 | D15: 0 | E15: 0 | F15: 0
A16: VA | B16: tasas +100 pb | C16: -818868.24 | D16: -818868.24 | E16: -818868.24 | F16: -818868.24
... A26: Inversiones | B26: tasas -100 pb | C26: 208896.55 | D26: 1808896.6 | E26: 208896.55 | F26: 1808896.6

Sheet Desarrollo_130
A1: Desarrollo de siniestros (par. 130)
A2: Estimación no descontada del último costo por año de accidente en cada cierre; última = pagado + pendiente (fórmula).
A4: Autos
A5: Cierre | B5: Año de accidente | C5: Pagado acumulado | D5: Pendiente no descontado | E5: Última estimación (fórmula) | F5: LIC descontado (sin ajuste por riesgo) | G5: Efecto del descuento (fórmula)
A6: 2023-12-31 | B6: 2023 | C6: 1401589.2 | D6: 2649679 | E6: =C6+D6 -> 4051268.3 | F6: 2503680.8 | G6: =F6-D6 -> -145998.18
A7: 2024-12-31 | B7: 2023 | C7: 3348181 | D7: 616105.51 | E7: =C7+D7 -> 3964286.5 | F7: 574505.84 | G7: =F7-D7 -> -41599.671
A8: 2024-12-31 | B8: 2024 | C8: 4009360.8 | D8: 4793743.8 | E8: =C8+D8 -> 8803104.6 | F8: 4516930.9 | G8: =F8-D8 -> -276812.92
A9: 2025-12-31 | B9: 2023 | C9: 3701037.6 | D9: 311704.36 | E9: =C9+D9 -> 4012742 | F9: 294354.56 | G9: =F9-D9 -> -17349.802
A10: 2025-12-31 | B10: 2024 | C10: 7215936.2 | D10: 1761852.9 | E10: =C10+D10 -> 8977789.1 | F10: 1659988.9 | G10: =F10-D10 -> -101864.01
A11: 2025-12-31 | B11: 2025 | C11: 4441340.5 | D11: 4390151.3 | E11: =C11+D11 -> 8831491.8 | F11: 4175358.6 | G11: =F11-D11 -> -214792.7
A14: Todo riesgo construcción
A15: Cierre | B15: Año de accidente | C15: Pagado acumulado | D15: Pendiente no descontado | E15: Última estimación (fórmula) | F15: LIC descontado (sin ajuste por riesgo) | G15: Efecto del descuento (fórmula)
A16: 2023-12-31 | B16: 2023 | C16: 5029.11 | D16: 23398.039 | E16: =C16+D16 -> 28427.149 | F16: 22610.088 | G16: =F16-D16 -> -787.95126
A17: 2024-12-31 | B17: 2023 | C17: 7194.99 | D17: 12274.921 | E17: =C17+D17 -> 19469.911 | F17: 12000.866 | G17: =F17-D17 -> -274.05513
A18: 2024-12-31 | B18: 2024 | C18: 298130.44 | D18: 583068.98 | E18: =C18+D18 -> 881199.42 | F18: 569153.63 | G18: =F18-D18 -> -13915.35
A19: 2025-12-31 | B19: 2023 | C19: 17949.85 | D19: 0.14258656 | E19: =C19+D19 -> 17949.993 | F19: 0.13903457 | G19: =F19-D19 -> -0.0035519866
A20: 2025-12-31 | B20: 2024 | C20: 1383205.2 | D20: 70134.553 | E20: =C20+D20 -> 1453339.7 | F20: 68824.913 | G20: =F20-D20 -> -1309.6401
A21: 2025-12-31 | B21: 2025 | C21: 531532.04 | D21: 1026024.5 | E21: =C21+D21 -> 1557556.6 | F21: 1005076.6 | G21: =F21-D21 -> -20947.897

Sheet Liquidez_132
A1: Flujos netos esperados no descontados al 31-dic-2025 (par. 132(b)(i))
A2: Salidas netas positivas. Vida incluye primas futuras (entradas, negativas) y el LIC; daños solo el LIC (132(b)).
A4: portfolio | B4: año 1 | C4: año 2 | D4: año 3 | E4: año 4 | F4: año 5 | G4: más de 5 años | H4: Total
A5: VT | B5: -3146086.4 | C5: -3047206.6 | D5: -2623935.5 | E5: -2195450 | F5: -1775231.6 | G5: 3583332.3 | H5: =SUM(B5:G5) -> -9204577.7
A6: VA | B6: -8171716.1 | C6: -7120727.9 | D6: -6074786.1 | E6: -5228058.2 | F6: -4635947 | G6: 1.7848267e+08 | H6: =SUM(B6:G6) -> 1.4725144e+08
A7: AUTO | B7: 3536595.2 | C7: 1394263.6 | D7: 755119.49 | E7: 394479.5 | F7: 197343.61 | G7: 185907.19 | H7: =SUM(B7:G7) -> 6463708.6
A8: INC | B8: 638499.1 | C8: 0 | D8: 0 | E8: 0 | F8: 0 | G8: 0 | H8: =SUM(B8:G8) -> 638499.1
A9: TRC | B9: 1096159.2 | C9: 0 | D9: 0 | E9: 0 | F9: 0 | G9: 0 | H9: =SUM(B9:G9) -> 1096159.2

Sheet Controles
A1: Resumen de controles
A2: Cada celda enlaza a un control de otra hoja; el total absoluto debe ser cero.
A4: Celda | B4: Valor
A5: EEFF!B18 | B5: =EEFF!B18 -> 0
A6: EEFF!C18 | B6: =EEFF!C18 -> 0
A7: EEFF!D18 | B7: =EEFF!D18 -> 0
A8: EEFF!B43 | B8: =EEFF!B43 -> 0
A9: EEFF!C43 | B9: =EEFF!C43 -> 0
A10: EEFF!D43 | B10: =EEFF!D43 -> 0
A11: Conc_100!B18 | B11: =Conc_100!B18 -> 5.2386895e-10
A12: Conc_100!C18 | B12: =Conc_100!C18 -> 0
A13: Conc_100!D18 | B13: =Conc_100!D18 -> 3.4197001e-10
A14: Conc_100!B33 | B14: =Conc_100!B33 -> 0
A15: Conc_100!C33 | B15: =Conc_100!C33 -> 0
A16: Conc_100!D33 | B16: =Conc_100!D33 -> 0
A17: Conc_100!B48 | B17: =Conc_100!B48 -> 0
A18: Conc_100!C48 | B18: =Conc_100!C48 -> 0
A19: Conc_100!D48 | B19: =Conc_100!D48 -> 0
A20: Conc_100!B65 | B20: =Conc_100!B65 -> 0
A21: Conc_100!C65 | B21: =Conc_100!C65 -> 0
A22: Conc_100!D65 | B22: =Conc_100!D65 -> -1.0641088e-10
A23: Conc_100!B80 | B23: =Conc_100!B80 -> 0
A24: Conc_100!C80 | B24: =Conc_100!C80 -> 0
A25: Conc_100!D80 | B25: =Conc_100!D80 -> -3.0377123e-10
A26: Conc_100!B95 | B26: =Conc_100!B95 -> 0
A27: Conc_100!C95 | B27: =Conc_100!C95 -> 0
A28: Conc_100!D95 | B28: =Conc_100!D95 -> -5.657057e-10
A29: Conc_100!B112 | B29: =Conc_100!B112 -> 0
A30: Conc_100!C112 | B30: =Conc_100!C112 -> 0
A31: Conc_100!D112 | B31: =Conc_100!D112 -> 0
A32: Conc_100!B127 | B32: =Conc_100!B127 -> 0
A33: Conc_100!C127 | B33: =Conc_100!C127 -> 0
A34: Conc_100!D127 | B34: =Conc_100!D127 -> 0
A35: Conc_100!B142 | B35: =Conc_100!B142 -> 0
A36: Conc_100!C142 | B36: =Conc_100!C142 -> 0
A37: Conc_100!D142 | B37: =Conc_100!D142 -> 0
A38: Conc_100!B159 | B38: =Conc_100!B159 -> 0
A39: Conc_100!C159 | B39: =Conc_100!C159 -> 0
A40: Conc_100!D159 | B40: =Conc_100!D159 -> 0
A41: Conc_100!B174 | B41: =Conc_100!B174 -> 0
A42: Conc_100!C174 | B42: =Conc_100!C174 -> 0
A43: Conc_100!D174 | B43: =Conc_100!D174 -> 0
A44: Conc_100!B189 | B44: =Conc_100!B189 -> 0
A45: Conc_100!C189 | B45: =Conc_100!C189 -> 0
A46: Conc_100!D189 | B46: =Conc_100!D189 -> 0
A47: Conc_100!B206 | B47: =Conc_100!B206 -> 0
A48: Conc_100!C206 | B48: =Conc_100!C206 -> 0
A49: Conc_100!D206 | B49: =Conc_100!D206 -> 0
A50: Conc_100!B221 | B50: =Conc_100!B221 -> 0
A51: Conc_100!C221 | B51: =Conc_100!C221 -> 0
A52: Conc_100!D221 | B52: =Conc_100!D221 -> 0
A53: Conc_100!B236 | B53: =Conc_100!B236 -> 0
A54: Conc_100!C236 | B54: =Conc_100!C236 -> 0
A55: Conc_100!D236 | B55: =Conc_100!D236 -> 0
A56: Conc_101!B20 | B56: =Conc_101!B20 -> 0
A57: Conc_101!C20 | B57: =Conc_101!C20 -> 0
A58: Conc_101!D20 | B58: =Conc_101!D20 -> 0
A59: Conc_101!B37 | B59: =Conc_101!B37 -> 0
A60: Conc_101!C37 | B60: =Conc_101!C37 -> 0
A61: Conc_101!D37 | B61: =Conc_101!D37 -> 0
A62: Conc_101!B54 | B62: =Conc_101!B54 -> 0
A63: Conc_101!C54 | B63: =Conc_101!C54 -> 0
A64: Conc_101!D54 | B64: =Conc_101!D54 -> 0
A65: Conc_101!B73 | B65: =Conc_101!B73 -> 0
A66: Conc_101!C73 | B66: =Conc_101!C73 -> 0
A67: Conc_101!D73 | B67: =Conc_101!D73 -> 0
A68: Conc_101!B90 | B68: =Conc_101!B90 -> 0
A69: Conc_101!C90 | B69: =Conc_101!C90 -> 0
A70: Conc_101!D90 | B70: =Conc_101!D90 -> 0
A71: Conc_101!B107 | B71: =Conc_101!B107 -> 0
A72: Conc_101!C107 | B72: =Conc_101!C107 -> 0
A73: Conc_101!D107 | B73: =Conc_101!D107 -> 0
A74: Conc_101!B126 | B74: =Conc_101!B126 -> 0
A75: Conc_101!C126 | B75: =Conc_101!C126 -> 0
A76: Conc_101!D126 | B76: =Conc_101!D126 -> 0
A77: Conc_101!B143 | B77: =Conc_101!B143 -> 0
A78: Conc_101!C143 | B78: =Conc_101!C143 -> 0
A79: Conc_101!D143 | B79: =Conc_101!D143 -> 0
A80: Conc_101!B160 | B80: =Conc_101!B160 -> 0
A81: Conc_101!C160 | B81: =Conc_101!C160 -> 0
A82: Conc_101!D160 | B82: =Conc_101!D160 -> 0
A83: Ingresos_106!J5 | B83: =Ingresos_106!J5 -> 0
A84: Ingresos_106!J6 | B84: =Ingresos_106!J6 -> 0
A85: Ingresos_106!J7 | B85: =Ingresos_106!J7 -> 0
A86: Ingresos_106!J8 | B86: =Ingresos_106!J8 -> 0
A87: Ingresos_106!J9 | B87: =Ingresos_106!J9 -> 0
A88: Ingresos_106!J10 | B88: =Ingresos_106!J10 -> 0
A89: NegocioNuevo_107!K5 | B89: =NegocioNuevo_107!K5 -> 1.0244548e-08
A90: NegocioNuevo_107!K6 | B90: =NegocioNuevo_107!K6 -> 0
A91: NegocioNuevo_107!K7 | B91: =NegocioNuevo_107!K7 -> 0
A92: NegocioNuevo_107!K8 | B92: =NegocioNuevo_107!K8 -> 0
A93: NegocioNuevo_107!K9 | B93: =NegocioNuevo_107!K9 -> 0
A94: NegocioNuevo_107!K10 | B94: =NegocioNuevo_107!K10 -> 0
A95: NegocioNuevo_107!K11 | B95: =NegocioNuevo_107!K11 -> 0
A96: NegocioNuevo_107!K12 | B96: =NegocioNuevo_107!K12 -> 0
A97: Suma de valores absolutos | B97: =SUMPRODUCT(ABS(B5:B96)) -> 1.2086275e-08
